ectcm/__init__.py
ectcm/download.py
ectcm/main.py
ectcm-0.0.4.dist-info/AUTHORS.rst
ectcm-0.0.4.dist-info/LICENSE.txt
ectcm-0.0.4.dist-info/METADATA
ectcm-0.0.4.dist-info/WHEEL
ectcm-0.0.4.dist-info/entry_points.txt
ectcm-0.0.4.dist-info/top_level.txt
ectcm-0.0.4.dist-info/RECORD
