Metadata-Version: 2.1
Name: ectcm
Version: 0.0.4
Summary: download data from https://www.ectcm.com/ and export as csv
Home-page: https://github.com/pyscaffold/pyscaffold/
Author: Eric NG
Author-email: mr5iff@gmail.com
License: mit
Project-URL: Documentation, https://pyscaffold.org/
Platform: any
Classifier: Development Status :: 4 - Beta
Classifier: Programming Language :: Python
Requires-Python: >=3.6
Requires-Dist: pandas
Requires-Dist: requests
Requires-Dist: tqdm
Provides-Extra: testing
Requires-Dist: pytest ; extra == 'testing'
Requires-Dist: pytest-cov ; extra == 'testing'
